checksum/__init__.py
checksum/__main__.py
checksum_cli-0.1.1.dist-info/DESCRIPTION.rst
checksum_cli-0.1.1.dist-info/METADATA
checksum_cli-0.1.1.dist-info/RECORD
checksum_cli-0.1.1.dist-info/WHEEL
checksum_cli-0.1.1.dist-info/entry_points.txt
checksum_cli-0.1.1.dist-info/metadata.json
checksum_cli-0.1.1.dist-info/top_level.txt
