Metadata-Version: 2.0
Name: checksum-cli
Version: 0.1.1
Summary: A command line interface program use for generate the checksum of file.
Home-page: https://github.com/cupen/checksum-cli
Author: cupen
Author-email: cupen@foxmail.com
License: WTFPL
Keywords: checksum cli
Platform: UNKNOWN
Classifier: Development Status :: 3 - Alpha
Classifier: Environment :: Console
Classifier: Intended Audience :: Developers
Classifier: Topic :: Utilities
Classifier: Programming Language :: Python :: 2.7
Classifier: Programming Language :: Python :: 3.4
Classifier: Programming Language :: Python :: 3.5
Classifier: Programming Language :: Python :: 3.6
Requires-Python: >=2.7.*,!=3.0.*,!=3.1.*,!=3.2.*,!=3.3.*
